<?xml version="1.0"?>
<page xmlns:xsi="http://www.w3.org/2001/XMLSchema-instance"
      xsi:noNamespaceSchemaLocation="urn:magento:framework:View/Layout/etc/page_configuration.xsd">
    <update handle="customer_account"/>
    <body>
    <referenceBlock name="page.main.title">
        <action method="setPageTitle">
            <argument translate="true" name="title" xsi:type="string">My Unit3</argument>
        </action>
    </referenceBlock>
    <referenceContainer name="content">
        <block class="RLTSquare\Unit3\Block\CustomerDetails" name="my_unit3" template="RLTSquare_Unit3::customer/account/unit3.phtml"/>
    </referenceContainer>
    </body>
</page>
